{"nodes":{"1":{"name":"item_1","left":52,"top":59,"type":"start","width":24,"height":24},"2":{"name":"item_2","left":142,"top":68,"type":"task","width":86,"height":24},"3":{"name":"item_3","left":250,"top":74,"type":"chat","width":86,"height":24},"4":{"name":"item_4","left":371,"top":75,"type":"end","width":24,"height":24},"8":{"name":"item_8","left":130,"top":146,"type":"node","width":86,"height":24},"11":{"name":"item_11","left":264,"top":159,"type":"state","width":86,"height":24}},"lines":{"Flow_line_5":{"type":"sl","from":"1","to":"2","name":"","marked":false},"Flow_line_6":{"type":"sl","from":"2","to":"3","name":"","marked":false},"Flow_line_7":{"type":"sl","from":"3","to":"4","name":"","marked":false},"Flow_line_9":{"type":"sl","from":"1","to":"8","name":"","marked":false},"Flow_line_10":{"type":"sl","from":"8","to":"3","name":"","marked":false},"Flow_line_12":{"type":"sl","from":"8","to":"11","name":"","marked":false}},"areas":{},"title":"请假流程","max":13}
